crosscompute/__init__.py
crosscompute/__main__.py
crosscompute/constants.py
crosscompute/dependencies.py
crosscompute/exceptions.py
crosscompute/settings.py
crosscompute/assets/LogoBrand-Horizontal-20230501.svg
crosscompute/assets/automation.html
crosscompute/assets/base.html
crosscompute/assets/button-panel.html
crosscompute/assets/checkbox-input-header.js
crosscompute/assets/checkbox-input.html
crosscompute/assets/checkbox-output-header.js
crosscompute/assets/checkbox-output.js
crosscompute/assets/configuration.yaml
crosscompute/assets/default.css
crosscompute/assets/embedded.css
crosscompute/assets/favicon.ico
crosscompute/assets/file-input-header.js
crosscompute/assets/file-input.html
crosscompute/assets/flex.css
crosscompute/assets/frame-output-header.js
crosscompute/assets/frame-output.js
crosscompute/assets/image-output-header.js
crosscompute/assets/image-output.js
crosscompute/assets/json-output-header.js
crosscompute/assets/json-output.js
crosscompute/assets/link-output-header.js
crosscompute/assets/link-output.js
crosscompute/assets/live.html
crosscompute/assets/markdown-output-header.js
crosscompute/assets/markdown-output.js
crosscompute/assets/pdf-output-header.js
crosscompute/assets/pdf-output.js
crosscompute/assets/pdf.css
crosscompute/assets/radio-input-header.js
crosscompute/assets/radio-input.html
crosscompute/assets/radio-output-header.js
crosscompute/assets/radio-output.js
crosscompute/assets/root.html
crosscompute/assets/service-worker.js
crosscompute/assets/step-body.js
crosscompute/assets/step.html
crosscompute/assets/string-input-header.js
crosscompute/assets/string-input.html
crosscompute/assets/string-input.js
crosscompute/assets/string-output-header.js
crosscompute/assets/string-output.js
crosscompute/assets/sw.js
crosscompute/assets/table-output-header.js
crosscompute/assets/table-output.js
crosscompute/assets/text-input.html
crosscompute/assets/text-input.js
crosscompute/assets/text-output-header.js
crosscompute/assets/text-output.js
crosscompute-0.9.4.13.dist-info/LICENSE.md
crosscompute-0.9.4.13.dist-info/METADATA
crosscompute-0.9.4.13.dist-info/WHEEL
crosscompute-0.9.4.13.dist-info/entry_points.txt
crosscompute-0.9.4.13.dist-info/top_level.txt
crosscompute-0.9.4.13.dist-info/zip-safe
crosscompute-0.9.4.13.dist-info/RECORD
