Metadata-Version: 2.1
Name: crosscompute
Version: 0.9.4.13
Summary: Automate your Jupyter notebooks and scripts as tools, reports, dashboards.
Home-page: https://crosscompute.com
Author: CrossCompute Inc.
Author-email: support@crosscompute.com
License: MIT
Project-URL: Bug Tracker, https://github.com/crosscompute/crosscompute/issues
Project-URL: Documentation, https://docs.crosscompute.com
Project-URL: Source Code, https://github.com/crosscompute/crosscompute
Platform: linux_i386
Platform: linux_x86_64
Classifier: Development Status :: 3 - Alpha
Classifier: Framework :: FastAPI
Classifier: Intended Audience :: Developers
Classifier: Intended Audience :: Information Technology
Classifier: Intended Audience :: Science/Research
Classifier: Intended Audience :: System Administrators
Classifier: License :: OSI Approved :: MIT License
Classifier: Operating System :: POSIX
Classifier: Programming Language :: Python :: 3
Classifier: Topic :: Internet :: WWW/HTTP :: Dynamic Content
Classifier: Topic :: Internet :: WWW/HTTP :: WSGI
Classifier: Topic :: Internet :: WWW/HTTP :: WSGI :: Application
Classifier: Topic :: Software Development :: Libraries :: Application Frameworks
Requires-Python: >=3.10
License-File: LICENSE.md
Requires-Dist: fastapi
Requires-Dist: importlib-metadata >=6.6.0
Requires-Dist: invisibleroads-macros-disk >=1.3.0
Requires-Dist: invisibleroads-macros-log >=1.0.6
Requires-Dist: invisibleroads-macros-process >=0.2.0
Requires-Dist: invisibleroads-macros-security >=1.0.3
Requires-Dist: invisibleroads-macros-text >=1.1.2
Requires-Dist: invisibleroads-macros-web[jinja,markdown,starlette] >=0.3.7
Requires-Dist: jinja2
Requires-Dist: nbconvert
Requires-Dist: nbformat
Requires-Dist: python-multipart
Requires-Dist: requests
Requires-Dist: ruamel.yaml
Requires-Dist: sse-starlette
Requires-Dist: tomli
Requires-Dist: uvicorn >=0.22.0
Requires-Dist: watchfiles
Provides-Extra: test
Requires-Dist: pytest-cov ; extra == 'test'
Requires-Dist: pytest-xdist ; extra == 'test'
